LICENSE
MANIFEST.in
README.rst
setup.py
django_stackhelper.egg-info/PKG-INFO
django_stackhelper.egg-info/SOURCES.txt
django_stackhelper.egg-info/dependency_links.txt
django_stackhelper.egg-info/requires.txt
django_stackhelper.egg-info/top_level.txt
stackhelper/__init__.py
stackhelper/management/__init__.py
stackhelper/management/commands/__init__.py
stackhelper/management/commands/stack_diff.py
stackhelper/management/commands/stack_generate.py