Metadata-Version: 1.0
Name: django-stackhelper
Version: 0.3
Summary: A Django application to help you configure other components of your deployment stack
Home-page: http://github.com/isotoma/django-stackhelper
Author: Doug Winter
Author-email: doug.winter@isotoma.com
License: Apache Software License
Platform: UNKNOWN
